shape_image/__init__.py
shape_image/collate.py
shape_image/io.py
shape_image/normalization.py
shape_image/image/__init__.py
shape_image/image/batched.py
shape_image/image/shape_image.py
shape_image/transforms/__init__.py
shape_image/transforms/affine.py
shape_image/transforms/base.py
shape_image/transforms/crop.py
shape_image/transforms/random.py
shape_image-0.0.1.dist-info/METADATA
shape_image-0.0.1.dist-info/WHEEL
shape_image-0.0.1.dist-info/top_level.txt
shape_image-0.0.1.dist-info/RECORD
