Metadata-Version: 2.1
Name: shape-image
Version: 0.0.1
Summary: This is a super duper package
Home-page: https://github.com/justusschock/shape-image
Author: Justus Schock
Author-email: justus.schock@posteo.de
License: UNKNOWN
Project-URL: source, https://github.com/justusschock/shape-image
Project-URL: tracker, https://github.com/justusschock/shape-image/issues
Keywords: deep learning,machine learning,pytorch,medical,AI
Platform: UNKNOWN
Classifier: Programming Language :: Python :: 3
Requires-Python: >=3.7
Requires-Dist: torch (==1.9.0)
Requires-Dist: pytorch-lightning (==1.3.8)
Requires-Dist: rising (==0.2.1)
Requires-Dist: scikit-learn (==0.24.2)
Requires-Dist: SimpleITK (==2.1.0)
